django_tour-0.7.0.dist-info/DESCRIPTION.rst
django_tour-0.7.0.dist-info/METADATA
django_tour-0.7.0.dist-info/metadata.json
django_tour-0.7.0.dist-info/RECORD
django_tour-0.7.0.dist-info/top_level.txt
django_tour-0.7.0.dist-info/WHEEL
tour/__init__.py
tour/api.py
tour/apps.py
tour/filters.py
tour/models.py
tour/serializers.py
tour/tours.py
tour/urls.py
tour/version.py
tour/views.py
tour/migrations/0001_initial.py
tour/migrations/__init__.py
tour/static/tour/build/tour.css
tour/static/tour/build/tour.js
tour/templates/tour/tour_navigation.html
tour/templatetags/__init__.py
tour/templatetags/tour_tags.py
tour/tests/__init__.py
tour/tests/api_tests.py
tour/tests/mocks.py
tour/tests/model_tests.py
tour/tests/serializer_tests.py
tour/tests/templatetag_tests.py
tour/tests/tour_tests.py
tour/tests/url_tests.py
tour/tests/view_tests.py
