Metadata-Version: 2.0
Name: django-tour
Version: 0.7.0
Summary: Require the django user to complete a series of steps with custom logic
Home-page: https://github.com/ambitioninc/django-tour
Author: Wes Okes
Author-email: wes.okes@gmail.com
License: MIT
Platform: UNKNOWN
Classifier: Programming Language :: Python
Classifier: Programming Language :: Python :: 2.7
Classifier: Programming Language :: Python :: 3.4
Classifier: Intended Audience :: Developers
Classifier: License :: OSI Approved :: MIT License
Classifier: Operating System :: OS Independent
Classifier: Framework :: Django
Classifier: Framework :: Django :: 1.7
Classifier: Framework :: Django :: 1.8
Requires-Dist: Django (>=1.7)
Requires-Dist: djangorestframework (>=2.3.13)
Requires-Dist: django-manager-utils (>=0.8.2)
Requires-Dist: django-filter (>=0.7)
